tiros/__init__.py
tiros/auth.py
tiros/cli.py
tiros/fetch_.py
tiros/server.py
tiros/util.py
tiros/version.py
tiros/tiros_viz/__init__.py
tiros/tiros_viz/app.py
tiros/tiros_viz/cp_data.py
tiros/tiros_viz/d3_data.py
tiros/tiros_viz/process_viz.py
tiros/tiros_viz/query_data.py
tiros/tiros_viz/render_error.py
tiros/tiros_viz/snapshot_data.py
tiros/tiros_viz/utils.py
tiros/tiros_viz/static/dashboard.json
tiros/tiros_viz/static/css/index.css
tiros/tiros_viz/static/data/README
tiros/tiros_viz/static/img/aws-selected.png
tiros/tiros_viz/static/img/aws.png
tiros/tiros_viz/static/img/igw-selected.png
tiros/tiros_viz/static/img/igw.png
tiros/tiros_viz/static/img/instance-selected.png
tiros/tiros_viz/static/img/instance.png
tiros/tiros_viz/static/img/subnet-selected.png
tiros/tiros_viz/static/img/subnet.png
tiros/tiros_viz/static/img/vpc-selected.png
tiros/tiros_viz/static/img/vpc.png
tiros/tiros_viz/static/js/tiros_async_requests.js
tiros/tiros_viz/static/js/tiros_network.js
tiros/tiros_viz/templates/dashboard.html
tiros/tiros_viz/templates/index.html
tiros-1.0.44.dist-info/DESCRIPTION.rst
tiros-1.0.44.dist-info/METADATA
tiros-1.0.44.dist-info/RECORD
tiros-1.0.44.dist-info/WHEEL
tiros-1.0.44.dist-info/entry_points.txt
tiros-1.0.44.dist-info/metadata.json
tiros-1.0.44.dist-info/top_level.txt
