Metadata-Version: 2.0
Name: tiros
Version: 1.0.44
Summary: UNKNOWN
Home-page: UNKNOWN
Author: UNKNOWN
Author-email: UNKNOWN
License: UNKNOWN
Platform: UNKNOWN
Requires-Dist: Flask (>=0.2)
Requires-Dist: boto3 (>=1.4.8)
Requires-Dist: datetime (>=4.1.1)
Requires-Dist: requests (>=2.11.1)
Requires-Dist: semantic-version (>=2.6.0)
